crazydoc/CrazydocParser.py
crazydoc/Observers.py
crazydoc/__init__.py
crazydoc/biotools.py
crazydoc/conf.py
crazydoc/crazydoc_writers.py
crazydoc/plots.py
crazydoc/version.py
crazydoc-0.2.2.dist-info/licenses/LICENSE
crazydoc-0.2.2.dist-info/METADATA
crazydoc-0.2.2.dist-info/WHEEL
crazydoc-0.2.2.dist-info/top_level.txt
crazydoc-0.2.2.dist-info/RECORD
