Metadata-Version: 2.4
Name: crazydoc
Version: 0.2.2
Summary: Read genetic sequences from stylized docx files
Author: Zulko
License-Expression: MIT
Project-URL: Homepage, https://github.com/Edinburgh-Genome-Foundry/crazydoc
Keywords: dna-sequence,bioinformatics,systems-biology,docx
License-File: LICENSE
Requires-Dist: biopython
Requires-Dist: python-docx
Dynamic: license-file
